MANIFEST.in
README.md
setup.py
trw_text_string/WordPairCounter.py
trw_text_string/__init__.py
trw_text_string.egg-info/PKG-INFO
trw_text_string.egg-info/SOURCES.txt
trw_text_string.egg-info/dependency_links.txt
trw_text_string.egg-info/top_level.txt