Metadata-Version: 1.0
Name: trw-text-string
Version: 0.0.5
Summary: Package for a challenge.
Home-page: UNKNOWN
Author: T Williams
Author-email: UNKNOWN
License: UNKNOWN
Platform: UNKNOWN
